[{"name": "VIDEO 4 (2)", "protocol": 8, "address": 6888, "command": 16}, {"name": "CD (2)", "protocol": 8, "address": 6888, "command": 19}, {"name": "TUNER (2)", "protocol": 8, "address": 6888, "command": 80}, {"name": "POWER ON", "protocol": 9, "address": 6888, "command": 84}, {"name": "POWER OFF", "protocol": 9, "address": 6888, "command": 85}, {"name": "DSP: PL2 MOVIE", "protocol": 8, "address": 6888, "command": 92}, {"name": "DSP: PL2 MUSIC", "protocol": 8, "address": 6888, "command": 93}, {"name": "VIDEO 2 (2)", "protocol": 8, "address": 6888, "command": 141}, {"name": "VIDEO 3 (2)", "protocol": 8, "address": 6888, "command": 142}, {"name": "POWER ON", "protocol": 8, "address": 6888, "command": 206}, {"name": "POWER OFF", "protocol": 8, "address": 6888, "command": 207}]