[{"name": "KEY_1", "protocol": 23, "address": 183, "command": 0}, {"name": "KEY_2", "protocol": 23, "address": 183, "command": 1}, {"name": "KEY_3", "protocol": 23, "address": 183, "command": 2}, {"name": "KEY_4", "protocol": 23, "address": 183, "command": 3}, {"name": "KEY_5", "protocol": 23, "address": 183, "command": 4}, {"name": "KEY_6", "protocol": 23, "address": 183, "command": 5}, {"name": "KEY_7", "protocol": 23, "address": 183, "command": 6}, {"name": "KEY_8", "protocol": 23, "address": 183, "command": 7}, {"name": "KEY_9", "protocol": 23, "address": 183, "command": 8}, {"name": "KEY_0", "protocol": 23, "address": 183, "command": 9}, {"name": "KEY_ENTER", "protocol": 23, "address": 183, "command": 11}, {"name": "KEY_CHANNELUP", "protocol": 23, "address": 183, "command": 16}, {"name": "KEY_CHANNELUP", "protocol": 23, "address": 183, "command": 16}, {"name": "KEY_CHANNELDOWN", "protocol": 23, "address": 183, "command": 17}, {"name": "KEY_CHANNELDOWN", "protocol": 23, "address": 183, "command": 17}, {"name": "KEY_VOLUMEUP", "protocol": 23, "address": 183, "command": 18}, {"name": "KEY_VOLUMEUP", "protocol": 23, "address": 183, "command": 18}, {"name": "KEY_VOLUMEDOWN", "protocol": 23, "address": 183, "command": 19}, {"name": "KEY_VOLUMEDOWN", "protocol": 23, "address": 183, "command": 19}, {"name": "KEY_MUTE", "protocol": 23, "address": 183, "command": 20}, {"name": "DSS_POWER", "protocol": 23, "address": 183, "command": 21}, {"name": "KEY_POWER", "protocol": 23, "address": 183, "command": 21}, {"name": "TV/VIDEO", "protocol": 23, "address": 183, "command": 37}, {"name": "KEY_POWER", "protocol": 23, "address": 183, "command": 46}, {"name": "KEY_POWER", "protocol": 23, "address": 183, "command": 47}, {"name": "KEY_MENU", "protocol": 23, "address": 183, "command": 56}, {"name": "DISPLAY", "protocol": 23, "address": 183, "command": 58}, {"name": "JUMP", "protocol": 23, "address": 183, "command": 59}, {"name": "INDEX", "protocol": 23, "address": 183, "command": 63}, {"name": "CATEGORY", "protocol": 23, "address": 183, "command": 68}, {"name": "KEY_AUDIO", "protocol": 23, "address": 183, "command": 71}, {"name": "CABLE", "protocol": 23, "address": 183, "command": 78}, {"name": "KEY_INFO", "protocol": 23, "address": 183, "command": 96}, {"name": "KEY_VIDEO", "protocol": 23, "address": 183, "command": 97}, {"name": "KEY_EXIT", "protocol": 23, "address": 183, "command": 99}, {"name": "TV/DSS", "protocol": 23, "address": 183, "command": 105}, {"name": "JUMP", "protocol": 23, "address": 183, "command": 108}, {"name": "KEY_INFO", "protocol": 23, "address": 183, "command": 110}, {"name": "KEY_FAVORITES", "protocol": 23, "address": 183, "command": 111}, {"name": "UP_ARROW", "protocol": 23, "address": 183, "command": 114}, {"name": "DOWN_ARROW", "protocol": 23, "address": 183, "command": 115}, {"name": "RIGHT_ARROW", "protocol": 23, "address": 183, "command": 116}, {"name": "LEFT_ARROW", "protocol": 23, "address": 183, "command": 117}, {"name": "KEY_SELECT", "protocol": 23, "address": 183, "command": 118}]