[{"name": "1", "protocol": 8, "address": 0, "command": 9}, {"name": "2", "protocol": 8, "address": 0, "command": 10}, {"name": "3", "protocol": 8, "address": 0, "command": 11}, {"name": "4", "protocol": 8, "address": 0, "command": 12}, {"name": "5", "protocol": 8, "address": 0, "command": 13}, {"name": "6", "protocol": 8, "address": 0, "command": 14}, {"name": "7", "protocol": 8, "address": 0, "command": 15}, {"name": "8", "protocol": 8, "address": 0, "command": 16}, {"name": "9", "protocol": 8, "address": 0, "command": 17}, {"name": "0", "protocol": 8, "address": 0, "command": 18}, {"name": "ENTER", "protocol": 8, "address": 0, "command": 20}, {"name": "+10", "protocol": 8, "address": 0, "command": 20}]