[{"name": "1", "protocol": 22, "address": 1, "command": 1}, {"name": "2", "protocol": 22, "address": 1, "command": 2}, {"name": "3", "protocol": 22, "address": 1, "command": 3}, {"name": "4", "protocol": 22, "address": 1, "command": 4}, {"name": "5", "protocol": 22, "address": 1, "command": 5}, {"name": "6", "protocol": 22, "address": 1, "command": 6}, {"name": "7", "protocol": 22, "address": 1, "command": 7}, {"name": "8", "protocol": 22, "address": 1, "command": 8}, {"name": "9", "protocol": 22, "address": 1, "command": 9}, {"name": "0", "protocol": 22, "address": 1, "command": 10}, {"name": "100", "protocol": 22, "address": 1, "command": 11}, {"name": "CHANNEL ^", "protocol": 22, "address": 1, "command": 17}, {"name": "CHANNEL V", "protocol": 22, "address": 1, "command": 18}, {"name": "INPUT", "protocol": 22, "address": 1, "command": 19}, {"name": "VOL +", "protocol": 22, "address": 1, "command": 20}, {"name": "VOL -", "protocol": 22, "address": 1, "command": 21}, {"name": "POWER", "protocol": 22, "address": 1, "command": 22}, {"name": "MUTE", "protocol": 22, "address": 1, "command": 23}, {"name": "DISPLAY", "protocol": 22, "address": 1, "command": 27}, {"name": "PREVIEW", "protocol": 22, "address": 1, "command": 28}, {"name": "MENU", "protocol": 22, "address": 1, "command": 32}, {"name": "QV", "protocol": 22, "address": 1, "command": 47}]