[{"name": "KEY_0", "protocol": 8, "address": 46596, "command": 0}, {"name": "KEY_1", "protocol": 8, "address": 46596, "command": 1}, {"name": "KEY_2", "protocol": 8, "address": 46596, "command": 2}, {"name": "KEY_3", "protocol": 8, "address": 46596, "command": 3}, {"name": "KEY_4", "protocol": 8, "address": 46596, "command": 4}, {"name": "KEY_5", "protocol": 8, "address": 46596, "command": 5}, {"name": "KEY_6", "protocol": 8, "address": 46596, "command": 6}, {"name": "KEY_7", "protocol": 8, "address": 46596, "command": 7}, {"name": "KEY_8", "protocol": 8, "address": 46596, "command": 8}, {"name": "KEY_9", "protocol": 8, "address": 46596, "command": 9}, {"name": "KEY_10CHANNELSUP", "protocol": 8, "address": 46596, "command": 12}, {"name": "KEY_EJECTCD", "protocol": 8, "address": 46596, "command": 16}, {"name": "KEY_STOP", "protocol": 8, "address": 46596, "command": 17}, {"name": "KEY_REWIND", "protocol": 8, "address": 46596, "command": 22}, {"name": "KEY_FORWARD", "protocol": 8, "address": 46596, "command": 23}, {"name": "Time_Display", "protocol": 8, "address": 46596, "command": 24}, {"name": "KEY_CLEAR", "protocol": 8, "address": 46596, "command": 26}, {"name": "KEY_PLAY", "protocol": 8, "address": 46596, "command": 31}, {"name": "KEY_RECORD", "protocol": 8, "address": 46596, "command": 80}, {"name": "Auto_Mark", "protocol": 8, "address": 46596, "command": 82}, {"name": "KEY_RECORD", "protocol": 8, "address": 46596, "command": 84}, {"name": "KEY_RECORD", "protocol": 8, "address": 46596, "command": 85}, {"name": "Synchro_Rec", "protocol": 8, "address": 46596, "command": 86}, {"name": "Timer", "protocol": 8, "address": 46596, "command": 87}, {"name": "KEY_PLAY", "protocol": 8, "address": 46596, "command": 154}, {"name": "KEY_POWER", "protocol": 8, "address": 46596, "command": 157}, {"name": "Display", "protocol": 8, "address": 46596, "command": 196}, {"name": "KEY_RECORD", "protocol": 8, "address": 46596, "command": 197}, {"name": "KEY_ENTER", "protocol": 8, "address": 46596, "command": 200}, {"name": "Track_Edit", "protocol": 8, "address": 46596, "command": 202}, {"name": "Programm", "protocol": 8, "address": 46596, "command": 219}]