[{"name": "STOP", "protocol": 11, "address": 45056, "command": 0}, {"name": "OPEN/CLOSE", "protocol": 11, "address": 45056, "command": 1}, {"name": "SEARCH <<", "protocol": 11, "address": 45056, "command": 4}, {"name": "SLOW/SEARCH <<", "protocol": 11, "address": 45056, "command": 4}, {"name": "SEARCH >>", "protocol": 11, "address": 45056, "command": 5}, {"name": "SLOW/SEARCH >>", "protocol": 11, "address": 45056, "command": 5}, {"name": "PAUSE", "protocol": 11, "address": 45056, "command": 6}, {"name": "STILL/PAUSE", "protocol": 11, "address": 45056, "command": 6}, {"name": "SLOW <", "protocol": 11, "address": 45056, "command": 7}, {"name": "PLAY", "protocol": 11, "address": 45056, "command": 10}, {"name": "SLOW >", "protocol": 11, "address": 45056, "command": 15}, {"name": "1", "protocol": 11, "address": 45056, "command": 16}, {"name": "2", "protocol": 11, "address": 45056, "command": 17}, {"name": "3", "protocol": 11, "address": 45056, "command": 18}, {"name": "4", "protocol": 11, "address": 45056, "command": 19}, {"name": "5", "protocol": 11, "address": 45056, "command": 20}, {"name": "6", "protocol": 11, "address": 45056, "command": 21}, {"name": "7", "protocol": 11, "address": 45056, "command": 22}, {"name": "8", "protocol": 11, "address": 45056, "command": 23}, {"name": "9", "protocol": 11, "address": 45056, "command": 24}, {"name": "0", "protocol": 11, "address": 45056, "command": 25}, {"name": "AUDIO MODE", "protocol": 11, "address": 45056, "command": 51}, {"name": "AUDIO", "protocol": 11, "address": 45056, "command": 51}, {"name": "POWER", "protocol": 11, "address": 45056, "command": 61}, {"name": "POWER ON", "protocol": 11, "address": 45056, "command": 62}, {"name": "POWER OFF", "protocol": 11, "address": 45056, "command": 63}, {"name": "HP-V.S.S.", "protocol": 11, "address": 45056, "command": 69}, {"name": "A-B REPEAT", "protocol": 11, "address": 45056, "command": 72}, {"name": "REPEAT A-B", "protocol": 11, "address": 45056, "command": 72}, {"name": "SIDE A/B", "protocol": 11, "address": 45056, "command": 72}, {"name": "A-B", "protocol": 11, "address": 45056, "command": 72}, {"name": "SKIP <<", "protocol": 11, "address": 45056, "command": 73}, {"name": "SKIP/SEARCH <<", "protocol": 11, "address": 45056, "command": 73}, {"name": "SKIP >>", "protocol": 11, "address": 45056, "command": 74}, {"name": "SKIP/SEARCH >>", "protocol": 11, "address": 45056, "command": 74}, {"name": "MENU", "protocol": 11, "address": 45056, "command": 128}, {"name": "MENU/PLAY LIST", "protocol": 11, "address": 45056, "command": 128}, {"name": "RETURN", "protocol": 11, "address": 45056, "command": 129}, {"name": "SELECT", "protocol": 11, "address": 45056, "command": 130}, {"name": "ENTER", "protocol": 11, "address": 45056, "command": 130}, {"name": "MENU ENTER", "protocol": 11, "address": 45056, "command": 130}, {"name": "CANCEL", "protocol": 11, "address": 45056, "command": 131}, {"name": "CLEAR", "protocol": 11, "address": 45056, "command": 131}, {"name": "CURSOR UP", "protocol": 11, "address": 45056, "command": 133}, {"name": "UP ARROW", "protocol": 11, "address": 45056, "command": 133}, {"name": "ARROW: UP", "protocol": 11, "address": 45056, "command": 133}, {"name": "MENU UP", "protocol": 11, "address": 45056, "command": 133}, {"name": "CURSOR DOWN", "protocol": 11, "address": 45056, "command": 134}, {"name": "DOWN ARROW", "protocol": 11, "address": 45056, "command": 134}, {"name": "ARROW: DOWN", "protocol": 11, "address": 45056, "command": 134}, {"name": "MENU DOWN", "protocol": 11, "address": 45056, "command": 134}, {"name": "CURSOR LEFT", "protocol": 11, "address": 45056, "command": 135}, {"name": "LEFT ARROW", "protocol": 11, "address": 45056, "command": 135}, {"name": "ARROW: LEFT", "protocol": 11, "address": 45056, "command": 135}, {"name": "MENU LEFT", "protocol": 11, "address": 45056, "command": 135}, {"name": "CURSOR RIGHT", "protocol": 11, "address": 45056, "command": 136}, {"name": "RIGHT ARROW", "protocol": 11, "address": 45056, "command": 136}, {"name": "ARROW: RIGHT", "protocol": 11, "address": 45056, "command": 136}, {"name": "MENU RIGHT", "protocol": 11, "address": 45056, "command": 136}, {"name": "+10", "protocol": 11, "address": 45056, "command": 137}, {"name": ">10", "protocol": 11, "address": 45056, "command": 137}, {"name": ">=10", "protocol": 11, "address": 45056, "command": 137}, {"name": "REPEAT MODE", "protocol": 11, "address": 45056, "command": 140}, {"name": "MODE", "protocol": 11, "address": 45056, "command": 140}, {"name": "PLAY MODE", "protocol": 11, "address": 45056, "command": 141}, {"name": "MARKER", "protocol": 11, "address": 45056, "command": 142}, {"name": "ANGLE", "protocol": 11, "address": 45056, "command": 144}, {"name": "SUBTITLE", "protocol": 11, "address": 45056, "command": 145}, {"name": "TITLE", "protocol": 11, "address": 45056, "command": 145}, {"name": "DISPLAY", "protocol": 11, "address": 45056, "command": 146}, {"name": "SUBTITLE OFF/ON", "protocol": 11, "address": 45056, "command": 147}, {"name": "ON/OFF", "protocol": 11, "address": 45056, "command": 147}, {"name": "ACTION", "protocol": 11, "address": 45056, "command": 148}, {"name": "SETUP", "protocol": 11, "address": 45056, "command": 148}, {"name": "PAUSE", "protocol": 11, "address": 45056, "command": 149}, {"name": "STILL/PAUSE", "protocol": 11, "address": 45056, "command": 149}, {"name": "DOWN CURSOR", "protocol": 11, "address": 45056, "command": 150}, {"name": "FRAME <<", "protocol": 11, "address": 45056, "command": 151}, {"name": "SEARCH <<", "protocol": 11, "address": 45056, "command": 151}, {"name": "FRAME >>", "protocol": 11, "address": 45056, "command": 152}, {"name": "SEARCH >>", "protocol": 11, "address": 45056, "command": 152}, {"name": "FL. DISP", "protocol": 11, "address": 45056, "command": 153}, {"name": "FL DISP.", "protocol": 11, "address": 45056, "command": 153}, {"name": "TITLE", "protocol": 11, "address": 45056, "command": 155}, {"name": "TOP MENU/DIRECT NAV", "protocol": 11, "address": 45056, "command": 155}, {"name": "VSS", "protocol": 11, "address": 45056, "command": 158}, {"name": "V.S.S.", "protocol": 11, "address": 45056, "command": 158}, {"name": "SP-V.S.S.", "protocol": 11, "address": 45056, "command": 158}, {"name": "GROUP", "protocol": 11, "address": 45056, "command": 224}, {"name": "AUDIO ONLY", "protocol": 11, "address": 45056, "command": 225}, {"name": "PAGE", "protocol": 11, "address": 45056, "command": 229}, {"name": "TEXT", "protocol": 11, "address": 45056, "command": 232}]