[{"name": "TAPE STOP", "protocol": 5, "address": 131, "command": 3}, {"name": "TAPE FFWD", "protocol": 5, "address": 131, "command": 6}, {"name": "TAPE REW", "protocol": 5, "address": 131, "command": 7}, {"name": "TAPE PLAY", "protocol": 5, "address": 131, "command": 12}, {"name": "TAPE PAUSE", "protocol": 5, "address": 131, "command": 13}, {"name": "TAPE1 STOP []", "protocol": 5, "address": 131, "command": 67}, {"name": "TAPE REC/PLAY", "protocol": 5, "address": 131, "command": 204}, {"name": "TAPE REC/PAUSE", "protocol": 5, "address": 131, "command": 205}]