[{"name": "POWER ON", "protocol": 4, "address": 1025, "command": 2}, {"name": "POWER OFF", "protocol": 4, "address": 1025, "command": 3}, {"name": "12V TRIGGER 1 ON", "protocol": 4, "address": 1025, "command": 12}, {"name": "12V TRIGGER 1 OFF", "protocol": 4, "address": 1025, "command": 13}, {"name": "12V TRIGGER 2 ON", "protocol": 4, "address": 1025, "command": 14}, {"name": "12V TRIGGER 2 OFF", "protocol": 4, "address": 1025, "command": 15}, {"name": "RETURN / BACK", "protocol": 4, "address": 1025, "command": 34}, {"name": "GUI MENU / SETUP", "protocol": 4, "address": 1025, "command": 35}, {"name": "TUNER MEMORY", "protocol": 4, "address": 1025, "command": 36}, {"name": "TUNER BAND TOGGLE AM/FM", "protocol": 4, "address": 1025, "command": 152}, {"name": "TUNER BAND FM", "protocol": 4, "address": 1025, "command": 153}, {"name": "TUNER BAND AM", "protocol": 4, "address": 1025, "command": 154}, {"name": "TUNER BAND XM", "protocol": 4, "address": 1025, "command": 155}, {"name": "INTERNET RADIO FAVORITE 1", "protocol": 4, "address": 1025, "command": 242}, {"name": "INTERNET RADIO FAVORITE 2", "protocol": 4, "address": 1025, "command": 243}, {"name": "INTERNET RADIO FAVORITE 3", "protocol": 4, "address": 1025, "command": 244}, {"name": "INTERNET RADIO FAVORITE 4", "protocol": 4, "address": 1025, "command": 245}, {"name": "QUICK SELECT / USER PRESET 1", "protocol": 4, "address": 1025, "command": 292}, {"name": "QUICK SELECT / USER PRESET 2", "protocol": 4, "address": 1025, "command": 293}, {"name": "QUICK SELECT / USER PRESET 3", "protocol": 4, "address": 1025, "command": 294}, {"name": "QUICK SELECT / USER PRESET 4", "protocol": 4, "address": 1025, "command": 295}, {"name": "QUICK SELECT / USER PRESET 5", "protocol": 4, "address": 1025, "command": 296}, {"name": "SURROUND MODE DIRECT / STEREO", "protocol": 4, "address": 1025, "command": 305}, {"name": "PURE DIRECT", "protocol": 4, "address": 1025, "command": 307}, {"name": "SURROUND MODE STANDARD", "protocol": 4, "address": 1025, "command": 308}, {"name": "SURROUND MODE AUTO", "protocol": 4, "address": 1025, "command": 324}, {"name": "SURROUND MODE AURO 3D PREVIOUS", "protocol": 4, "address": 1025, "command": 332}, {"name": "SURROUND MODE DSP SIMULATION", "protocol": 4, "address": 1025, "command": 336}, {"name": "SURROUND MODE MULTI CHANNEL", "protocol": 4, "address": 1025, "command": 337}, {"name": "SURROUND MODE NEURAL", "protocol": 4, "address": 1025, "command": 347}, {"name": "SURROUND MODE DOLBY ATMOS", "protocol": 4, "address": 1025, "command": 348}, {"name": "SURROUND MODE AURO 3D NEXT", "protocol": 4, "address": 1025, "command": 349}, {"name": "INPUT MODE HDMI", "protocol": 4, "address": 1025, "command": 357}, {"name": "INPUT MODE DIGITAL", "protocol": 4, "address": 1025, "command": 359}, {"name": "INPUT MODE DECODE", "protocol": 4, "address": 1025, "command": 364}, {"name": "VOLUME UP", "protocol": 4, "address": 1025, "command": 368}, {"name": "VOLUME DOWN", "protocol": 4, "address": 1025, "command": 369}, {"name": "VOLUME MUTE", "protocol": 4, "address": 1025, "command": 370}, {"name": "CHANNEL LEVEL", "protocol": 4, "address": 1025, "command": 378}, {"name": "SUBWOOFER 2 LEVEL UP", "protocol": 4, "address": 1025, "command": 410}, {"name": "SUBWOOFER 2 LEVEL DOWN", "protocol": 4, "address": 1025, "command": 411}, {"name": "DOLBY TFL SPEAKER LEVEL UP", "protocol": 4, "address": 1025, "command": 417}, {"name": "DOLBY TFL SPEAKER LEVEL DOWN", "protocol": 4, "address": 1025, "command": 418}, {"name": "DOLBY TFR SPEAKER LEVEL UP", "protocol": 4, "address": 1025, "command": 419}, {"name": "DOLBY TFR SPEAKER LEVEL DOWN", "protocol": 4, "address": 1025, "command": 420}, {"name": "DOLBY TML SPEAKER LEVEL UP", "protocol": 4, "address": 1025, "command": 421}, {"name": "DOLBY TML SPEAKER LEVEL DOWN", "protocol": 4, "address": 1025, "command": 422}, {"name": "DOLBY TMR SPEAKER LEVEL UP", "protocol": 4, "address": 1025, "command": 423}, {"name": "DOLBY TMR SPEAKER LEVEL DOWN", "protocol": 4, "address": 1025, "command": 424}, {"name": "DOLBY TRL SPEAKER LEVEL UP", "protocol": 4, "address": 1025, "command": 425}, {"name": "DOLBY TRL SPEAKER LEVEL DOWN", "protocol": 4, "address": 1025, "command": 426}, {"name": "DOLBY TRR SPEAKER LEVEL UP", "protocol": 4, "address": 1025, "command": 427}, {"name": "DOLBY TRR SPEAKER LEVEL DOWN", "protocol": 4, "address": 1025, "command": 428}, {"name": "DOLBY RHL SPEAKER LEVEL UP", "protocol": 4, "address": 1025, "command": 429}, {"name": "DOLBY RHL SPEAKER LEVEL DOWN", "protocol": 4, "address": 1025, "command": 430}, {"name": "DOLBY RHR SPEAKER LEVEL UP", "protocol": 4, "address": 1025, "command": 431}, {"name": "DOLBY RHR SPEAKER LEVEL DOWN", "protocol": 4, "address": 1025, "command": 432}, {"name": "DOLBY LF SPEAKER LEVEL UP", "protocol": 4, "address": 1025, "command": 433}, {"name": "DOLBY LF SPEAKER LEVEL DOWN", "protocol": 4, "address": 1025, "command": 434}, {"name": "DOLBY RF SPEAKER LEVEL UP", "protocol": 4, "address": 1025, "command": 435}, {"name": "DOLBY RF SPEAKER LEVEL DOWN", "protocol": 4, "address": 1025, "command": 436}, {"name": "DOLBY SL SPEAKER LEVEL UP", "protocol": 4, "address": 1025, "command": 437}, {"name": "DOLBY SL SPEAKER LEVEL DOWN", "protocol": 4, "address": 1025, "command": 438}, {"name": "DOLBY SR SPEAKER LEVEL UP", "protocol": 4, "address": 1025, "command": 439}, {"name": "DOLBY SR SPEAKER LEVEL DOWN", "protocol": 4, "address": 1025, "command": 440}, {"name": "DOLBY LB SPEAKER LEVEL UP", "protocol": 4, "address": 1025, "command": 441}, {"name": "DOLBY LB SPEAKER LEVEL DOWN", "protocol": 4, "address": 1025, "command": 442}, {"name": "DOLBY RB SPEAKER LEVEL UP", "protocol": 4, "address": 1025, "command": 443}, {"name": "DOLBY RB SPEAKER LEVEL DOWN", "protocol": 4, "address": 1025, "command": 444}, {"name": "LFC ON", "protocol": 4, "address": 1025, "command": 445}, {"name": "LFC OFF", "protocol": 4, "address": 1025, "command": 446}, {"name": "LFC TOGGLE ON/OFF", "protocol": 4, "address": 1025, "command": 456}, {"name": "DSX SELECT", "protocol": 4, "address": 1025, "command": 529}, {"name": "DYNAMIC VOLUME TOGGLE MODE", "protocol": 4, "address": 1025, "command": 545}, {"name": "DYNAMIC EQ TOGGLE ON/OFF", "protocol": 4, "address": 1025, "command": 547}, {"name": "RESTORER MODE", "protocol": 4, "address": 1025, "command": 548}, {"name": "DYNAMIC EQ/VOLUME TOGGLE MODE", "protocol": 4, "address": 1025, "command": 549}, {"name": "FRONT SPEAKER A", "protocol": 4, "address": 1025, "command": 550}, {"name": "FRONT SPEAKER B", "protocol": 4, "address": 1025, "command": 552}, {"name": "FRONT SPEAKER A+B", "protocol": 4, "address": 1025, "command": 554}, {"name": "RESTORER OFF", "protocol": 4, "address": 1025, "command": 556}, {"name": "RESTORER MODE 1", "protocol": 4, "address": 1025, "command": 557}, {"name": "RESTORER MODE 2", "protocol": 4, "address": 1025, "command": 558}, {"name": "RESTORER MODE 3", "protocol": 4, "address": 1025, "command": 559}, {"name": "SS AUDIO DELAY", "protocol": 4, "address": 1025, "command": 620}, {"name": "AUDIO DELAY MODE", "protocol": 4, "address": 1025, "command": 620}, {"name": "AUDIO DELAY UP", "protocol": 4, "address": 1025, "command": 621}, {"name": "AUDIO DELAY DOWN", "protocol": 4, "address": 1025, "command": 622}, {"name": "INFO / OSD", "protocol": 4, "address": 1025, "command": 624}, {"name": "DSX ON HEIGHT", "protocol": 4, "address": 1025, "command": 642}, {"name": "DSX ON WIDE", "protocol": 4, "address": 1025, "command": 643}, {"name": "DSX OFF", "protocol": 4, "address": 1025, "command": 644}, {"name": "STATUS REQUEST", "protocol": 4, "address": 1025, "command": 645}, {"name": "DSX ON WIDE+HEIGHT", "protocol": 4, "address": 1025, "command": 647}, {"name": "INPUT IPOD", "protocol": 4, "address": 1025, "command": 667}, {"name": "HDMI MONITOR SELECT 1", "protocol": 4, "address": 1025, "command": 669}, {"name": "HDMI MONITOR SELECT 2", "protocol": 4, "address": 1025, "command": 670}, {"name": "INPUT AUX/NET/USB/ONLINE MUSIC", "protocol": 4, "address": 1025, "command": 711}, {"name": "INPUT TUNER XM", "protocol": 4, "address": 1025, "command": 714}, {"name": "INPUT DTU / HD RADIO", "protocol": 4, "address": 1025, "command": 715}, {"name": "INPUT AUX/NET", "protocol": 4, "address": 1025, "command": 716}, {"name": "INPUT AUX/IPOD/DOCK", "protocol": 4, "address": 1025, "command": 717}, {"name": "INPUT AUX/USB", "protocol": 4, "address": 1025, "command": 718}, {"name": "INPUT HD RADIO", "protocol": 4, "address": 1025, "command": 719}, {"name": "INPUT BD", "protocol": 4, "address": 1025, "command": 721}, {"name": "INPUT GAME", "protocol": 4, "address": 1025, "command": 725}, {"name": "INPUT GAME 2", "protocol": 4, "address": 1025, "command": 727}, {"name": "INPUT VCR4", "protocol": 4, "address": 1025, "command": 728}, {"name": "INPUT AUX 2", "protocol": 4, "address": 1025, "command": 730}, {"name": "INPUT BD/DVD/HDP", "protocol": 4, "address": 1025, "command": 732}, {"name": "INPUT VCR 1/2", "protocol": 4, "address": 1025, "command": 733}, {"name": "INPUT VCR 3/4", "protocol": 4, "address": 1025, "command": 734}, {"name": "INPUT VCR/DVR/MEDIA PLAYER", "protocol": 4, "address": 1025, "command": 735}, {"name": "MULTEQ XT 32 TOGGLE MODE", "protocol": 4, "address": 1025, "command": 736}, {"name": "INPUT INTERNET RADIO", "protocol": 4, "address": 1025, "command": 741}, {"name": "DYNAMIC EQ ON + DYNAMIC VOLUME OFF", "protocol": 4, "address": 1025, "command": 746}, {"name": "DYNAMIC EQ OFF + DYNAMIC VOLUME OFF", "protocol": 4, "address": 1025, "command": 747}, {"name": "DYNAMIC VOLUME HEAVY/MIDNIGHT", "protocol": 4, "address": 1025, "command": 748}, {"name": "DYNAMIC VOLUME MEDIUM/EVENING", "protocol": 4, "address": 1025, "command": 749}, {"name": "DYNAMIC VOLUME LIGHT/DAY", "protocol": 4, "address": 1025, "command": 750}, {"name": "INPUT BLUETOOTH", "protocol": 4, "address": 1025, "command": 751}, {"name": "HDMI MONITOR SELECT", "protocol": 4, "address": 1025, "command": 753}, {"name": "HDMI MONITOR SCALE/RESOLUTION", "protocol": 4, "address": 1025, "command": 754}, {"name": "HDMI ASPECT RADIO 16:9", "protocol": 4, "address": 1025, "command": 757}, {"name": "HDMI ASPECT RADIO 4:3", "protocol": 4, "address": 1025, "command": 758}, {"name": "DYNAMIC EQ REF LEVEL 0DB", "protocol": 4, "address": 1025, "command": 760}, {"name": "DYNAMIC EQ REF LEVEL 5DB", "protocol": 4, "address": 1025, "command": 761}, {"name": "DYNAMIC EQ REF LEVEL 10DB", "protocol": 4, "address": 1025, "command": 762}, {"name": "DYNAMIC EQ REF LEVEL 15DB", "protocol": 4, "address": 1025, "command": 763}, {"name": "INPUT SPOTIFY", "protocol": 4, "address": 1025, "command": 764}, {"name": "INPUT PANDORA", "protocol": 4, "address": 1025, "command": 765}, {"name": "NET/USB CURSOR/ARROW UP", "protocol": 4, "address": 1025, "command": 768}, {"name": "NET/USB CURSOR/ARROW DOWN", "protocol": 4, "address": 1025, "command": 769}, {"name": "NET/USB CURSOR/ARROW LEFT", "protocol": 4, "address": 1025, "command": 770}, {"name": "NET/USB CURSOR/ARROW RIGHT", "protocol": 4, "address": 1025, "command": 771}, {"name": "NET/USB ENTER/PLAY/PAUSE", "protocol": 4, "address": 1025, "command": 772}, {"name": "NET/USB PLAY", "protocol": 4, "address": 1025, "command": 773}, {"name": "NET/USB PAUSE", "protocol": 4, "address": 1025, "command": 774}, {"name": "NET/USB STOP", "protocol": 4, "address": 1025, "command": 775}, {"name": "NET/USB SKIP PLUS", "protocol": 4, "address": 1025, "command": 776}, {"name": "NET/USB SKIP MINUS", "protocol": 4, "address": 1025, "command": 777}, {"name": "NET/USB REPEAT ONE", "protocol": 4, "address": 1025, "command": 778}, {"name": "NET/USB REPEAT OFF", "protocol": 4, "address": 1025, "command": 779}, {"name": "NET/USB RANDOM ON", "protocol": 4, "address": 1025, "command": 780}, {"name": "NET/USB RANDOM OFF", "protocol": 4, "address": 1025, "command": 781}, {"name": "NET/USB REPEAT ALL", "protocol": 4, "address": 1025, "command": 785}, {"name": "GRAPHIC EQ TOGGLE ON/OFF", "protocol": 4, "address": 1025, "command": 789}, {"name": "GRAPHIC EQ ON", "protocol": 4, "address": 1025, "command": 792}, {"name": "GRAPHIC EQ OFF", "protocol": 4, "address": 1025, "command": 799}, {"name": "IPOD CURSOR/ARROW UP", "protocol": 4, "address": 1025, "command": 800}, {"name": "IPOD CURSOR/ARROW DOWN", "protocol": 4, "address": 1025, "command": 801}, {"name": "IPOD CURSOR/ARROW LEFT", "protocol": 4, "address": 1025, "command": 802}, {"name": "IPOD CURSOR/ARROW RIGHT", "protocol": 4, "address": 1025, "command": 803}, {"name": "IPOD ENTER", "protocol": 4, "address": 1025, "command": 804}, {"name": "IPOD PLAY/PAUSE", "protocol": 4, "address": 1025, "command": 805}, {"name": "IPOD STOP", "protocol": 4, "address": 1025, "command": 807}, {"name": "IPOD SKIP PLUS/FORWARD", "protocol": 4, "address": 1025, "command": 808}, {"name": "IPOD SKIP MINUS/REVERSE", "protocol": 4, "address": 1025, "command": 809}, {"name": "IPOD SEARCH FORWARD", "protocol": 4, "address": 1025, "command": 810}, {"name": "IPOD SEARCH REVERSE", "protocol": 4, "address": 1025, "command": 811}, {"name": "IPOD REPEAT ONE", "protocol": 4, "address": 1025, "command": 812}, {"name": "IPOD REPEAT ALL", "protocol": 4, "address": 1025, "command": 813}, {"name": "IPOD REPEAT OFF", "protocol": 4, "address": 1025, "command": 814}, {"name": "IPOD SHUFFLE SONGS", "protocol": 4, "address": 1025, "command": 815}, {"name": "IPOD SHUFFLE ALBUMS", "protocol": 4, "address": 1025, "command": 816}, {"name": "IPOD SHUFFLE OFF", "protocol": 4, "address": 1025, "command": 817}, {"name": "IPOD MENU", "protocol": 4, "address": 1025, "command": 818}, {"name": "IPOD MODE BROWSE", "protocol": 4, "address": 1025, "command": 819}, {"name": "IPOD MODE REMOTE", "protocol": 4, "address": 1025, "command": 820}, {"name": "HDMI CONTROL/CEC ON", "protocol": 4, "address": 1025, "command": 826}, {"name": "HDMI CONTROL/CEC OFF", "protocol": 4, "address": 1025, "command": 827}, {"name": "HDMI AUDIO OUT TOGGLE TV/AMP", "protocol": 4, "address": 1025, "command": 829}, {"name": "HDMI AUDIO OUT TV", "protocol": 4, "address": 1025, "command": 830}, {"name": "HDMI AUDIO OUT AMP", "protocol": 4, "address": 1025, "command": 831}, {"name": "PARTY", "protocol": 4, "address": 1025, "command": 835}, {"name": "SLEEP", "protocol": 4, "address": 1025, "command": 836}, {"name": "INSTA PREVIEW TOGGLE ON/OFF", "protocol": 4, "address": 1025, "command": 859}, {"name": "INSTA PREVIEW ON", "protocol": 4, "address": 1025, "command": 870}, {"name": "INSTA PREVIEW OFF", "protocol": 4, "address": 1025, "command": 871}, {"name": "ECO MODE TOGGLE", "protocol": 4, "address": 1025, "command": 872}, {"name": "ECO MODE OFF", "protocol": 4, "address": 1025, "command": 873}, {"name": "ECO MODE ON", "protocol": 4, "address": 1025, "command": 874}, {"name": "ECO MODE AUTO", "protocol": 4, "address": 1025, "command": 875}, {"name": "OPTION", "protocol": 4, "address": 1025, "command": 949}, {"name": "REPEAT", "protocol": 4, "address": 1025, "command": 956}, {"name": "RANDOM/SHUFFLE", "protocol": 4, "address": 1025, "command": 957}, {"name": "USB DIRECT PLAY", "protocol": 4, "address": 1025, "command": 958}, {"name": "FAVORITE DIRECT PLAY", "protocol": 4, "address": 1025, "command": 959}, {"name": "TUNER PRESET CHANNEL UP", "protocol": 4, "address": 1025, "command": 972}, {"name": "TUNER PRESET CHANNEL DOWN", "protocol": 4, "address": 1025, "command": 973}, {"name": "TUNER PRESET CHANNEL SHIFT", "protocol": 4, "address": 1025, "command": 974}, {"name": "TUNER PRESET SEARCH/RDS", "protocol": 4, "address": 1025, "command": 983}, {"name": "PLAY/PAUSE", "protocol": 4, "address": 1025, "command": 992}, {"name": "STOP", "protocol": 4, "address": 1025, "command": 993}, {"name": "TUNER PRESET SKIP/TUNE DOWN", "protocol": 4, "address": 1025, "command": 995}, {"name": "TUNER PRESET SKIP/TUNE UP", "protocol": 4, "address": 1025, "command": 996}]