[{"name": "STORE", "protocol": 8, "address": 51877, "command": 4}, {"name": "KEY_SAT", "protocol": 8, "address": 51877, "command": 5}, {"name": "KEY_0", "protocol": 8, "address": 51877, "command": 6}, {"name": "KEY_9", "protocol": 8, "address": 51877, "command": 7}, {"name": "KEY_POWER", "protocol": 8, "address": 51877, "command": 8}, {"name": "KEY_8", "protocol": 8, "address": 51877, "command": 12}, {"name": "KEY_7", "protocol": 8, "address": 51877, "command": 13}, {"name": "KEY_6", "protocol": 8, "address": 51877, "command": 14}, {"name": "KEY_5", "protocol": 8, "address": 51877, "command": 15}, {"name": "KEY_CHANNELUP", "protocol": 8, "address": 51877, "command": 18}, {"name": "KEY_CHANNELDOWN", "protocol": 8, "address": 51877, "command": 19}, {"name": "PL", "protocol": 8, "address": 51877, "command": 20}, {"name": "T_DOWN", "protocol": 8, "address": 51877, "command": 21}, {"name": "T_UP", "protocol": 8, "address": 51877, "command": 24}, {"name": "M/S", "protocol": 8, "address": 51877, "command": 25}, {"name": "SET", "protocol": 8, "address": 51877, "command": 26}, {"name": "V/H", "protocol": 8, "address": 51877, "command": 27}, {"name": "KEY_4", "protocol": 8, "address": 51877, "command": 28}, {"name": "KEY_3", "protocol": 8, "address": 51877, "command": 29}, {"name": "KEY_2", "protocol": 8, "address": 51877, "command": 30}, {"name": "KEY_1", "protocol": 8, "address": 51877, "command": 31}]