[{"name": "STANDBY", "protocol": 8, "address": 124, "command": 128}, {"name": "OPEN/CLOSE", "protocol": 8, "address": 124, "command": 129}, {"name": "PLAY", "protocol": 8, "address": 124, "command": 130}, {"name": "PAUSE", "protocol": 8, "address": 124, "command": 131}, {"name": "STOP", "protocol": 8, "address": 124, "command": 133}, {"name": "SEARCH -", "protocol": 8, "address": 124, "command": 134}, {"name": "SEARCH +", "protocol": 8, "address": 124, "command": 135}, {"name": "SLOW -", "protocol": 8, "address": 124, "command": 142}, {"name": "SLOW +", "protocol": 8, "address": 124, "command": 143}, {"name": "0", "protocol": 8, "address": 124, "command": 147}, {"name": "1", "protocol": 8, "address": 124, "command": 148}, {"name": "2", "protocol": 8, "address": 124, "command": 149}, {"name": "3", "protocol": 8, "address": 124, "command": 150}, {"name": "4", "protocol": 8, "address": 124, "command": 151}, {"name": "5", "protocol": 8, "address": 124, "command": 152}, {"name": "6", "protocol": 8, "address": 124, "command": 153}, {"name": "7", "protocol": 8, "address": 124, "command": 154}, {"name": "8", "protocol": 8, "address": 124, "command": 155}, {"name": "9", "protocol": 8, "address": 124, "command": 156}, {"name": "SEARCH", "protocol": 8, "address": 124, "command": 158}, {"name": "CLEAR", "protocol": 8, "address": 124, "command": 159}, {"name": "PROGRAM", "protocol": 8, "address": 124, "command": 160}, {"name": "REPEAT", "protocol": 8, "address": 124, "command": 163}, {"name": "A/B", "protocol": 8, "address": 124, "command": 164}, {"name": "ON SCREEN", "protocol": 8, "address": 124, "command": 166}, {"name": "STATUS", "protocol": 8, "address": 124, "command": 168}, {"name": "SUB TITLE", "protocol": 8, "address": 124, "command": 168}, {"name": "SETUP", "protocol": 8, "address": 124, "command": 172}, {"name": "AUDIO", "protocol": 8, "address": 124, "command": 173}, {"name": "ANGLE", "protocol": 8, "address": 124, "command": 174}, {"name": "TOP MENU", "protocol": 8, "address": 124, "command": 177}, {"name": "CURSOR DOWN", "protocol": 8, "address": 124, "command": 179}, {"name": "CURSOR UP", "protocol": 8, "address": 124, "command": 180}, {"name": "CURSOR LEFT", "protocol": 8, "address": 124, "command": 181}, {"name": "CURSOR RIGHT", "protocol": 8, "address": 124, "command": 182}, {"name": "RETURN", "protocol": 8, "address": 124, "command": 183}, {"name": "CURSOR ENTER", "protocol": 8, "address": 124, "command": 184}, {"name": "SKIP -", "protocol": 8, "address": 124, "command": 185}, {"name": "SKIP +", "protocol": 8, "address": 124, "command": 186}, {"name": "POP UP MENU", "protocol": 8, "address": 124, "command": 207}, {"name": "ZOOM", "protocol": 8, "address": 124, "command": 215}, {"name": "DIGEST", "protocol": 8, "address": 124, "command": 226}, {"name": "RED", "protocol": 8, "address": 124, "command": 233}, {"name": "GREEN", "protocol": 8, "address": 124, "command": 234}, {"name": "MARKER", "protocol": 8, "address": 124, "command": 234}, {"name": "BLUE", "protocol": 8, "address": 124, "command": 235}, {"name": "YELLOW", "protocol": 8, "address": 124, "command": 236}, {"name": "PIP", "protocol": 8, "address": 124, "command": 237}, {"name": "2ND AUDIO", "protocol": 8, "address": 124, "command": 238}, {"name": "HOME", "protocol": 8, "address": 124, "command": 239}, {"name": "REPEAT OFF", "protocol": 8, "address": 124, "command": 243}, {"name": "POWER ON", "protocol": 8, "address": 124, "command": 246}, {"name": "POWER OFF", "protocol": 8, "address": 124, "command": 247}]