[{"name": "FMMode", "protocol": 8, "address": 191, "command": 0}, {"name": "KEY_VOLUMEUP", "protocol": 8, "address": 191, "command": 2}, {"name": "Reset", "protocol": 8, "address": 191, "command": 3}, {"name": "Test", "protocol": 8, "address": 191, "command": 5}, {"name": "DolbyDigital", "protocol": 8, "address": 191, "command": 6}, {"name": "Bypass", "protocol": 8, "address": 191, "command": 7}, {"name": "KEY_DVD", "protocol": 8, "address": 191, "command": 8}, {"name": "KEY_CD", "protocol": 8, "address": 191, "command": 9}, {"name": "Delay", "protocol": 8, "address": 191, "command": 10}, {"name": "KEY_1", "protocol": 8, "address": 191, "command": 13}, {"name": "Config", "protocol": 8, "address": 191, "command": 15}, {"name": "KEY_MUTE", "protocol": 8, "address": 191, "command": 16}, {"name": "KEY_5", "protocol": 8, "address": 191, "command": 17}, {"name": "KEY_9", "protocol": 8, "address": 191, "command": 18}, {"name": "KEY_SLEEP", "protocol": 8, "address": 191, "command": 20}, {"name": "KEY_6", "protocol": 8, "address": 191, "command": 21}, {"name": "KEY_7", "protocol": 8, "address": 191, "command": 23}, {"name": "DSPDown", "protocol": 8, "address": 191, "command": 24}, {"name": "KEY_2", "protocol": 8, "address": 191, "command": 25}, {"name": "KEY_3", "protocol": 8, "address": 191, "command": 27}, {"name": "Opt", "protocol": 8, "address": 191, "command": 29}, {"name": "ChLevel", "protocol": 8, "address": 191, "command": 30}, {"name": "Coax", "protocol": 8, "address": 191, "command": 31}, {"name": "X_KEY_3Stereo", "protocol": 8, "address": 191, "command": 64}, {"name": "KEY_4", "protocol": 8, "address": 191, "command": 65}, {"name": "KEY_VOLUMEDOWN", "protocol": 8, "address": 191, "command": 66}, {"name": "Dimmer", "protocol": 8, "address": 191, "command": 67}, {"name": "DTS", "protocol": 8, "address": 191, "command": 68}, {"name": "KEY_DOWN", "protocol": 8, "address": 191, "command": 69}, {"name": "KEY_8", "protocol": 8, "address": 191, "command": 70}, {"name": "ProLogic", "protocol": 8, "address": 191, "command": 71}, {"name": "KEY_VCR", "protocol": 8, "address": 191, "command": 72}, {"name": "KEY_TAPE", "protocol": 8, "address": 191, "command": 73}, {"name": "KEY_AUX", "protocol": 8, "address": 191, "command": 74}, {"name": "Direct", "protocol": 8, "address": 191, "command": 80}, {"name": "PreTun", "protocol": 8, "address": 191, "command": 83}, {"name": "Memo", "protocol": 8, "address": 191, "command": 85}, {"name": "Auto", "protocol": 8, "address": 191, "command": 86}, {"name": "FMAM", "protocol": 8, "address": 191, "command": 87}, {"name": "KEY_0", "protocol": 8, "address": 191, "command": 89}, {"name": "KEY_UP", "protocol": 8, "address": 191, "command": 94}, {"name": "DSPUp", "protocol": 8, "address": 191, "command": 95}]