[{"name": "num1", "protocol": 22, "address": 1, "command": 1}, {"name": "num2", "protocol": 22, "address": 1, "command": 2}, {"name": "num3", "protocol": 22, "address": 1, "command": 3}, {"name": "num4", "protocol": 22, "address": 1, "command": 4}, {"name": "num5", "protocol": 22, "address": 1, "command": 5}, {"name": "num6", "protocol": 22, "address": 1, "command": 6}, {"name": "num7", "protocol": 22, "address": 1, "command": 7}, {"name": "num8", "protocol": 22, "address": 1, "command": 8}, {"name": "num9", "protocol": 22, "address": 1, "command": 9}, {"name": "num0", "protocol": 22, "address": 1, "command": 10}, {"name": "KEY_CHANNELUP", "protocol": 22, "address": 1, "command": 17}, {"name": "KEY_CHANNELDOWN", "protocol": 22, "address": 1, "command": 18}, {"name": "tv_video", "protocol": 22, "address": 1, "command": 19}, {"name": "KEY_VOLUMEUP", "protocol": 22, "address": 1, "command": 20}, {"name": "KEY_VOLUMEDOWN", "protocol": 22, "address": 1, "command": 21}, {"name": "KEY_POWER", "protocol": 22, "address": 1, "command": 22}, {"name": "vol_mute", "protocol": 22, "address": 1, "command": 23}, {"name": "KEY_POWER", "protocol": 22, "address": 1, "command": 27}, {"name": "screen_time", "protocol": 22, "address": 1, "command": 28}, {"name": "screen_blank", "protocol": 22, "address": 1, "command": 50}, {"name": "screen_smaller", "protocol": 22, "address": 1, "command": 51}, {"name": "screen_switch", "protocol": 22, "address": 1, "command": 52}, {"name": "screen_close", "protocol": 22, "address": 1, "command": 53}, {"name": "screen_s", "protocol": 22, "address": 1, "command": 54}, {"name": "screen_bigger", "protocol": 22, "address": 1, "command": 55}, {"name": "screen_question", "protocol": 22, "address": 1, "command": 56}, {"name": "num_switch", "protocol": 22, "address": 1, "command": 60}, {"name": "p_c", "protocol": 22, "address": 1, "command": 61}, {"name": "pr", "protocol": 22, "address": 1, "command": 65}, {"name": "KEY_RED", "protocol": 22, "address": 1, "command": 72}, {"name": "KEY_GREEN", "protocol": 22, "address": 1, "command": 73}, {"name": "KEY_YELLOW", "protocol": 22, "address": 1, "command": 74}, {"name": "KEY_BLUE", "protocol": 22, "address": 1, "command": 75}, {"name": "screen_info", "protocol": 22, "address": 1, "command": 76}, {"name": "KEY_F", "protocol": 22, "address": 1, "command": 95}, {"name": "KEY_P", "protocol": 22, "address": 1, "command": 96}, {"name": "KEY_S", "protocol": 22, "address": 1, "command": 97}]