[{"name": "POWER TOGGLE", "protocol": 8, "address": 32, "command": 0}, {"name": "AUTO", "protocol": 8, "address": 32, "command": 1}, {"name": "INFO", "protocol": 8, "address": 32, "command": 2}, {"name": "BRIGHTNESS +", "protocol": 8, "address": 32, "command": 3}, {"name": "CONTRAST +", "protocol": 8, "address": 32, "command": 4}, {"name": "COLOR +", "protocol": 8, "address": 32, "command": 5}, {"name": "VOLUME +", "protocol": 8, "address": 32, "command": 6}, {"name": "BRIGHTNESS -", "protocol": 8, "address": 32, "command": 7}, {"name": "CONTRAST -", "protocol": 8, "address": 32, "command": 8}, {"name": "COLOR -", "protocol": 8, "address": 32, "command": 9}, {"name": "VOLUME -", "protocol": 8, "address": 32, "command": 10}, {"name": "VGA", "protocol": 8, "address": 32, "command": 11}, {"name": "DVI", "protocol": 8, "address": 32, "command": 12}, {"name": "COMPOSITE", "protocol": 8, "address": 32, "command": 13}, {"name": "AV-MUTE", "protocol": 8, "address": 32, "command": 14}, {"name": "COMPONENT", "protocol": 8, "address": 32, "command": 15}, {"name": "S-VIDEO", "protocol": 8, "address": 32, "command": 16}, {"name": "STILL", "protocol": 8, "address": 32, "command": 17}, {"name": "TIME", "protocol": 8, "address": 32, "command": 18}, {"name": "ASPECT", "protocol": 8, "address": 32, "command": 19}, {"name": "MENU", "protocol": 8, "address": 32, "command": 20}, {"name": "LEFT KEY", "protocol": 8, "address": 32, "command": 21}, {"name": "RIGHT KEY", "protocol": 8, "address": 32, "command": 22}, {"name": "GAMMA -", "protocol": 8, "address": 32, "command": 23}, {"name": "GAMMA +", "protocol": 8, "address": 32, "command": 24}, {"name": "* (STAR)", "protocol": 8, "address": 32, "command": 25}, {"name": "1", "protocol": 8, "address": 32, "command": 26}, {"name": "2", "protocol": 8, "address": 32, "command": 27}, {"name": "3", "protocol": 8, "address": 32, "command": 28}, {"name": "4", "protocol": 8, "address": 32, "command": 29}, {"name": "5", "protocol": 8, "address": 32, "command": 30}, {"name": "6", "protocol": 8, "address": 32, "command": 31}, {"name": "7", "protocol": 8, "address": 32, "command": 32}, {"name": "8", "protocol": 8, "address": 32, "command": 33}, {"name": "9", "protocol": 8, "address": 32, "command": 34}, {"name": "STORE", "protocol": 8, "address": 32, "command": 35}, {"name": "0", "protocol": 8, "address": 32, "command": 36}, {"name": "RECALL", "protocol": 8, "address": 32, "command": 37}, {"name": "ARROW UP", "protocol": 8, "address": 32, "command": 38}, {"name": "ARROW LEFT", "protocol": 8, "address": 32, "command": 39}, {"name": "OK", "protocol": 8, "address": 32, "command": 40}, {"name": "ARROW RIGHT", "protocol": 8, "address": 32, "command": 41}, {"name": "ARROW DOWN", "protocol": 8, "address": 32, "command": 42}, {"name": "POWER ON", "protocol": 8, "address": 32, "command": 128}, {"name": "POWER OFF", "protocol": 8, "address": 32, "command": 129}]