[{"name": "POWER TOG", "protocol": 8, "address": 120, "command": 15}, {"name": "0", "protocol": 8, "address": 120, "command": 16}, {"name": "FM/XM: 0", "protocol": 8, "address": 120, "command": 16}, {"name": "1", "protocol": 8, "address": 120, "command": 17}, {"name": "FM/XM: 1", "protocol": 8, "address": 120, "command": 17}, {"name": "2", "protocol": 8, "address": 120, "command": 18}, {"name": "FM/XM: 2", "protocol": 8, "address": 120, "command": 18}, {"name": "3", "protocol": 8, "address": 120, "command": 19}, {"name": "FM/XM: 3", "protocol": 8, "address": 120, "command": 19}, {"name": "4", "protocol": 8, "address": 120, "command": 20}, {"name": "FM/XM: 4", "protocol": 8, "address": 120, "command": 20}, {"name": "5", "protocol": 8, "address": 120, "command": 21}, {"name": "FM/XM: 5", "protocol": 8, "address": 120, "command": 21}, {"name": "6", "protocol": 8, "address": 120, "command": 22}, {"name": "FM/XM: 6", "protocol": 8, "address": 120, "command": 22}, {"name": "7", "protocol": 8, "address": 120, "command": 23}, {"name": "FM/XM: 7", "protocol": 8, "address": 120, "command": 23}, {"name": "8", "protocol": 8, "address": 120, "command": 24}, {"name": "FM/XM: 8", "protocol": 8, "address": 120, "command": 24}, {"name": "9", "protocol": 8, "address": 120, "command": 25}, {"name": "FM/XM: 9", "protocol": 8, "address": 120, "command": 25}, {"name": "FM UP", "protocol": 8, "address": 120, "command": 27}, {"name": "SUR UPP", "protocol": 8, "address": 120, "command": 27}, {"name": "PRESET +", "protocol": 8, "address": 120, "command": 27}, {"name": "FM/XM: PRESET +", "protocol": 8, "address": 120, "command": 27}, {"name": "FM DOWN", "protocol": 8, "address": 120, "command": 28}, {"name": "SUR NER", "protocol": 8, "address": 120, "command": 28}, {"name": "PRESET -", "protocol": 8, "address": 120, "command": 28}, {"name": "FM/XM: PRESET -", "protocol": 8, "address": 120, "command": 28}, {"name": "FM A-E", "protocol": 8, "address": 120, "command": 29}, {"name": "XM CATEGORY +", "protocol": 8, "address": 120, "command": 29}, {"name": "FM/XM: PG/CAT+", "protocol": 8, "address": 120, "command": 29}, {"name": "VOLUME +", "protocol": 8, "address": 120, "command": 30}, {"name": "VOLUME UP", "protocol": 8, "address": 120, "command": 30}, {"name": "VOLUME -", "protocol": 8, "address": 120, "command": 31}, {"name": "VOLUME DOWN", "protocol": 8, "address": 120, "command": 31}, {"name": "CH LEVEL", "protocol": 8, "address": 120, "command": 72}, {"name": "LEVEL", "protocol": 8, "address": 120, "command": 72}, {"name": "LEVEL TOG", "protocol": 8, "address": 120, "command": 72}, {"name": "DSP: LEVEL TOGGLE", "protocol": 8, "address": 120, "command": 72}, {"name": "INPUT AUX1", "protocol": 8, "address": 120, "command": 73}, {"name": "INPUT VCR", "protocol": 8, "address": 120, "command": 73}, {"name": "INPUT AUX 1", "protocol": 8, "address": 120, "command": 73}, {"name": "INPUT: AUX 1", "protocol": 8, "address": 120, "command": 73}, {"name": "INPUT DVD", "protocol": 8, "address": 120, "command": 74}, {"name": "INPUT: DVD", "protocol": 8, "address": 120, "command": 74}, {"name": "INPUT FM", "protocol": 8, "address": 120, "command": 75}, {"name": "INPUT: XM/FM", "protocol": 8, "address": 120, "command": 75}, {"name": "DISPLAY", "protocol": 8, "address": 120, "command": 78}, {"name": "SLEEP", "protocol": 8, "address": 120, "command": 79}, {"name": "SLEEP TOG", "protocol": 8, "address": 120, "command": 79}, {"name": "SLEEP: TOGGLE", "protocol": 8, "address": 120, "command": 79}, {"name": "4", "protocol": 8, "address": 120, "command": 80}, {"name": "SUR STEREO", "protocol": 8, "address": 120, "command": 80}, {"name": "BEAM-STEREO", "protocol": 8, "address": 120, "command": 80}, {"name": "STEREO/5 CH STEREO", "protocol": 8, "address": 120, "command": 80}, {"name": "DSP: BMSTEREOTOG", "protocol": 8, "address": 120, "command": 80}, {"name": "TEST", "protocol": 8, "address": 120, "command": 95}, {"name": "TEST MODE", "protocol": 8, "address": 120, "command": 95}, {"name": "TEST MODE TOG", "protocol": 8, "address": 120, "command": 95}, {"name": "TEST (DOLBY)", "protocol": 8, "address": 120, "command": 95}, {"name": "TEST TOGGLE", "protocol": 8, "address": 120, "command": 95}, {"name": "SEARCH MODE ALL CH", "protocol": 8, "address": 120, "command": 103}, {"name": "FM/XM: SRCHMD ALL", "protocol": 8, "address": 120, "command": 103}, {"name": "SEARCH MODE PREST", "protocol": 8, "address": 120, "command": 104}, {"name": "FM/XM: SRCHMPRES", "protocol": 8, "address": 120, "command": 104}, {"name": "DEMO 1 ON", "protocol": 9, "address": 120, "command": 107}, {"name": "DEMO 1 ON", "protocol": 8, "address": 120, "command": 107}, {"name": "DEMO 1 OFF", "protocol": 9, "address": 120, "command": 108}, {"name": "DEMO 1 OFF", "protocol": 8, "address": 120, "command": 108}, {"name": "TRUBASS MID", "protocol": 9, "address": 120, "command": 109}, {"name": "DEMO 2 ON", "protocol": 9, "address": 120, "command": 109}, {"name": "TRUBASS: MID", "protocol": 8, "address": 120, "command": 109}, {"name": "DSP: TBASS ON MID", "protocol": 8, "address": 120, "command": 109}, {"name": "TRUBASS DEEP", "protocol": 9, "address": 120, "command": 110}, {"name": "DEMO 2 OFF", "protocol": 9, "address": 120, "command": 110}, {"name": "TRUBASS: DEEP", "protocol": 8, "address": 120, "command": 110}, {"name": "DSP: TBASS ON DEEP", "protocol": 8, "address": 120, "command": 110}, {"name": "TRUBASS OFF", "protocol": 9, "address": 120, "command": 111}, {"name": "TRUBASS: OFF", "protocol": 8, "address": 120, "command": 111}, {"name": "DSP: TBASS OFF", "protocol": 8, "address": 120, "command": 111}, {"name": "PRESET MEMORY A", "protocol": 8, "address": 120, "command": 112}, {"name": "VOLUME MEMORY A", "protocol": 8, "address": 120, "command": 112}, {"name": "PRESET RECALL A", "protocol": 8, "address": 120, "command": 113}, {"name": "VOLUME RECALL A", "protocol": 8, "address": 120, "command": 113}, {"name": "PRESET MEMORY B", "protocol": 8, "address": 120, "command": 114}, {"name": "VOLUME MEMORY B", "protocol": 8, "address": 120, "command": 114}, {"name": "PRESET RECALL B", "protocol": 8, "address": 120, "command": 115}, {"name": "VOLUME RECALL B", "protocol": 8, "address": 120, "command": 115}, {"name": "PRESET MEMORY C", "protocol": 8, "address": 120, "command": 116}, {"name": "VOLUME MEMORY C", "protocol": 8, "address": 120, "command": 116}, {"name": "PRESET RECALL C", "protocol": 8, "address": 120, "command": 117}, {"name": "VOLUME RECALL C", "protocol": 8, "address": 120, "command": 117}, {"name": "MEMORY SAVE USER1", "protocol": 8, "address": 120, "command": 118}, {"name": "MEMORY LOAD USER1", "protocol": 8, "address": 120, "command": 119}, {"name": "MEMORY SAVE USER2", "protocol": 8, "address": 120, "command": 120}, {"name": "MEMORY LOAD USER2", "protocol": 8, "address": 120, "command": 121}, {"name": "MEMORY SAVE USER3", "protocol": 8, "address": 120, "command": 122}, {"name": "MEMORY LOAD USER3", "protocol": 8, "address": 120, "command": 123}, {"name": "TV EQUAL VOL ON", "protocol": 9, "address": 120, "command": 124}, {"name": "TV MODE: ON", "protocol": 8, "address": 120, "command": 124}, {"name": "DSP: TV MODE ON", "protocol": 8, "address": 120, "command": 124}, {"name": "INPUT XM", "protocol": 8, "address": 120, "command": 125}, {"name": "INPUT: XM", "protocol": 8, "address": 120, "command": 125}, {"name": "POWER ON", "protocol": 8, "address": 120, "command": 126}, {"name": "POWER OFF", "protocol": 8, "address": 120, "command": 127}, {"name": "VOL MODE", "protocol": 8, "address": 120, "command": 138}, {"name": "NIGHT TOG", "protocol": 8, "address": 120, "command": 138}, {"name": "VOLUME MODE", "protocol": 8, "address": 120, "command": 138}, {"name": "DSP: VOL MODE TOG", "protocol": 8, "address": 120, "command": 138}, {"name": "TRUBASS TOG", "protocol": 9, "address": 120, "command": 139}, {"name": "SRS TRUBASS", "protocol": 8, "address": 120, "command": 139}, {"name": "DSP: TBASS TOGG", "protocol": 8, "address": 120, "command": 139}, {"name": "INPUTMODE", "protocol": 8, "address": 120, "command": 141}, {"name": "INPUT MODE: TOGGLE", "protocol": 8, "address": 120, "command": 141}, {"name": "CURSOR UP", "protocol": 8, "address": 120, "command": 142}, {"name": "SET MENU UP", "protocol": 8, "address": 120, "command": 142}, {"name": "UP", "protocol": 8, "address": 120, "command": 142}, {"name": "SET: CURSOR UP", "protocol": 8, "address": 120, "command": 142}, {"name": "CURSOR DOWN", "protocol": 8, "address": 120, "command": 143}, {"name": "SET MENU DOWN", "protocol": 8, "address": 120, "command": 143}, {"name": "DOWN", "protocol": 8, "address": 120, "command": 143}, {"name": "SET: CURSOR DOWN", "protocol": 8, "address": 120, "command": 143}, {"name": "SUR DECODE", "protocol": 8, "address": 120, "command": 153}, {"name": "SURROUND TOG", "protocol": 8, "address": 120, "command": 153}, {"name": "DSP: T SURROUND", "protocol": 8, "address": 120, "command": 153}, {"name": "0", "protocol": 8, "address": 120, "command": 155}, {"name": "SUR OFF", "protocol": 8, "address": 120, "command": 155}, {"name": "DSP OFF", "protocol": 9, "address": 120, "command": 155}, {"name": "CINEMA DSP: OFF", "protocol": 8, "address": 120, "command": 155}, {"name": "DSP: CDSP OFF", "protocol": 8, "address": 120, "command": 155}, {"name": "VOLUME MUTE", "protocol": 8, "address": 120, "command": 156}, {"name": "MUTE TOG", "protocol": 8, "address": 120, "command": 156}, {"name": "NIGHT MODE OFF", "protocol": 8, "address": 120, "command": 156}, {"name": "MUTE TOGGLE", "protocol": 8, "address": 120, "command": 156}, {"name": "MENU", "protocol": 8, "address": 120, "command": 157}, {"name": "SET MENU", "protocol": 8, "address": 120, "command": 157}, {"name": "SET MENU TOG", "protocol": 8, "address": 120, "command": 157}, {"name": "SET: SET MENU", "protocol": 8, "address": 120, "command": 157}, {"name": "CURSOR RIGHT", "protocol": 8, "address": 120, "command": 158}, {"name": "SET MENU +", "protocol": 8, "address": 120, "command": 158}, {"name": "SET MENU RIGHT", "protocol": 8, "address": 120, "command": 158}, {"name": "RIGHT", "protocol": 8, "address": 120, "command": 158}, {"name": "SET: CURSOR RIGHT", "protocol": 8, "address": 120, "command": 158}, {"name": "CURSOR LEFT", "protocol": 8, "address": 120, "command": 159}, {"name": "SUR A-E", "protocol": 8, "address": 120, "command": 159}, {"name": "SET MENU -", "protocol": 8, "address": 120, "command": 159}, {"name": "SET MENU LEFT", "protocol": 8, "address": 120, "command": 159}, {"name": "LEFT", "protocol": 8, "address": 120, "command": 159}, {"name": "SET: CURSOR LEFT", "protocol": 8, "address": 120, "command": 159}, {"name": "MUTE ON", "protocol": 8, "address": 120, "command": 162}, {"name": "AUTO SETUP", "protocol": 8, "address": 120, "command": 163}, {"name": "AUTO INTELLIBEAM", "protocol": 9, "address": 120, "command": 163}, {"name": "INTELLIBEAM START", "protocol": 8, "address": 120, "command": 163}, {"name": "MUTE OFF", "protocol": 8, "address": 120, "command": 163}, {"name": "SET: IBM START TRIGG", "protocol": 8, "address": 120, "command": 163}, {"name": "+10", "protocol": 8, "address": 120, "command": 165}, {"name": "FM PRESET/TUNE", "protocol": 8, "address": 120, "command": 168}, {"name": "PRESET/TUNE MODE", "protocol": 8, "address": 120, "command": 168}, {"name": "FM/XM: PRES/TUNE", "protocol": 8, "address": 120, "command": 168}, {"name": "TUNING-/PRESET-", "protocol": 8, "address": 120, "command": 169}, {"name": "FM/XM: TUN/PRE-", "protocol": 8, "address": 120, "command": 169}, {"name": "TUNING+/PRESET+", "protocol": 8, "address": 120, "command": 170}, {"name": "FM/XM: TUN/PRE+", "protocol": 8, "address": 120, "command": 170}, {"name": "PRESET E CATEGORY", "protocol": 8, "address": 120, "command": 171}, {"name": "FM/XM: PAGE E", "protocol": 8, "address": 120, "command": 171}, {"name": "PRESET D CATEGORY", "protocol": 8, "address": 120, "command": 172}, {"name": "FM/XM: PAGE D", "protocol": 8, "address": 120, "command": 172}, {"name": "PRESET C CATEGORY", "protocol": 8, "address": 120, "command": 173}, {"name": "FM/XM: PAGE C", "protocol": 8, "address": 120, "command": 173}, {"name": "PRESET B CATEGORY", "protocol": 8, "address": 120, "command": 174}, {"name": "FM/XM: PAGE B", "protocol": 8, "address": 120, "command": 174}, {"name": "PRESET A CATEGORY", "protocol": 8, "address": 120, "command": 175}, {"name": "FM/XM: PAGE A", "protocol": 8, "address": 120, "command": 175}, {"name": "AUTO SEARCH -", "protocol": 8, "address": 120, "command": 176}, {"name": "FM/XM: AUTO SRCH-", "protocol": 8, "address": 120, "command": 176}, {"name": "AUTO SEARCH +", "protocol": 8, "address": 120, "command": 177}, {"name": "FM/XM: AUTO SRCH+", "protocol": 8, "address": 120, "command": 177}, {"name": "FM MEMORY", "protocol": 8, "address": 120, "command": 178}, {"name": "MEMORY", "protocol": 8, "address": 120, "command": 178}, {"name": "FM/XM: MEMORY", "protocol": 8, "address": 120, "command": 178}, {"name": "INPUT FM", "protocol": 8, "address": 120, "command": 182}, {"name": "INPUT: FM", "protocol": 8, "address": 120, "command": 182}, {"name": "FM SEARCH", "protocol": 8, "address": 120, "command": 183}, {"name": "FM/XM: SRCH MODE", "protocol": 8, "address": 120, "command": 183}, {"name": "XM DISPLAY", "protocol": 8, "address": 120, "command": 184}, {"name": "FM/XM: XM DISPLAY", "protocol": 8, "address": 120, "command": 184}, {"name": "XM CATEGORY -", "protocol": 8, "address": 120, "command": 187}, {"name": "FM/XM: PG/CAT-", "protocol": 8, "address": 120, "command": 187}, {"name": "INPUT AUX3", "protocol": 8, "address": 120, "command": 188}, {"name": "INPUT AUX 3", "protocol": 8, "address": 120, "command": 188}, {"name": "INPUT: AUX 3", "protocol": 8, "address": 120, "command": 188}, {"name": "XM ENTER", "protocol": 8, "address": 120, "command": 189}, {"name": "FM/XM: XM ENTER", "protocol": 8, "address": 120, "command": 189}, {"name": "RETURN", "protocol": 8, "address": 120, "command": 192}, {"name": "SET MENU RETURN", "protocol": 8, "address": 120, "command": 192}, {"name": "SET: RETURN", "protocol": 8, "address": 120, "command": 192}, {"name": "CURSOR ENTER", "protocol": 8, "address": 120, "command": 193}, {"name": "SET MENU SELECT", "protocol": 8, "address": 120, "command": 193}, {"name": "SET MENU ENTER", "protocol": 8, "address": 120, "command": 193}, {"name": "SET: ENTER", "protocol": 8, "address": 120, "command": 193}, {"name": "1", "protocol": 8, "address": 120, "command": 194}, {"name": "SUR 5BEAM", "protocol": 8, "address": 120, "command": 194}, {"name": "BEAM-5BEAM", "protocol": 8, "address": 120, "command": 194}, {"name": "5 BEAM MODE", "protocol": 8, "address": 120, "command": 194}, {"name": "DSP: BM 5 BEAM", "protocol": 8, "address": 120, "command": 194}, {"name": "2", "protocol": 8, "address": 120, "command": 195}, {"name": "SUR ST+3BEAM", "protocol": 8, "address": 120, "command": 195}, {"name": "BEAM-ST+3BEAM", "protocol": 8, "address": 120, "command": 195}, {"name": "ST+3 BEAM MODE", "protocol": 8, "address": 120, "command": 195}, {"name": "DSP: BM ST+3 BEA", "protocol": 8, "address": 120, "command": 195}, {"name": "3", "protocol": 8, "address": 120, "command": 196}, {"name": "SUR 3BEAM", "protocol": 8, "address": 120, "command": 196}, {"name": "BEAM-3BEAM", "protocol": 8, "address": 120, "command": 196}, {"name": "3 BEAM MODE", "protocol": 8, "address": 120, "command": 196}, {"name": "DSP: BM 3 BEAM", "protocol": 8, "address": 120, "command": 196}, {"name": "5", "protocol": 8, "address": 120, "command": 197}, {"name": "SUR MY BEAM", "protocol": 8, "address": 120, "command": 197}, {"name": "BEAM-TARGET", "protocol": 9, "address": 120, "command": 197}, {"name": "BEAM-MY BEAM AUTO", "protocol": 9, "address": 120, "command": 197}, {"name": "DSP: BM MY BEAM", "protocol": 8, "address": 120, "command": 197}, {"name": "6", "protocol": 8, "address": 120, "command": 198}, {"name": "SUR MY SUR", "protocol": 8, "address": 120, "command": 198}, {"name": "DSP: BM MY SURR.", "protocol": 8, "address": 120, "command": 198}, {"name": "ENHANCER", "protocol": 8, "address": 120, "command": 203}, {"name": "MUSIC ENHANCER TOGGL", "protocol": 8, "address": 120, "command": 203}, {"name": "DSP: M ENHAN TOG", "protocol": 8, "address": 120, "command": 203}, {"name": "DSP: T MUSIC ENHA", "protocol": 8, "address": 120, "command": 203}, {"name": "POWER", "protocol": 8, "address": 120, "command": 204}, {"name": "8", "protocol": 8, "address": 120, "command": 217}, {"name": "SUR MOVIE", "protocol": 8, "address": 120, "command": 217}, {"name": "DSP MOVIE TOG", "protocol": 9, "address": 120, "command": 217}, {"name": "CINEMA DSP (MOVIE) T", "protocol": 8, "address": 120, "command": 217}, {"name": "DSP: T CDSP MOVIE", "protocol": 8, "address": 120, "command": 217}, {"name": "7", "protocol": 8, "address": 120, "command": 218}, {"name": "SUR MUSIC", "protocol": 8, "address": 120, "command": 218}, {"name": "DSP MUSIC TOG", "protocol": 9, "address": 120, "command": 218}, {"name": "CINEMA DSP (MUSIC) T", "protocol": 8, "address": 120, "command": 218}, {"name": "DSP: T CDSP MUSIC", "protocol": 8, "address": 120, "command": 218}, {"name": "9", "protocol": 8, "address": 120, "command": 219}, {"name": "SUR SPORTS", "protocol": 8, "address": 120, "command": 219}, {"name": "CINEMA DSP (SPORTS)", "protocol": 8, "address": 120, "command": 219}, {"name": "DSP: CDSP SPORTS", "protocol": 8, "address": 120, "command": 219}, {"name": "INPUT AUX2", "protocol": 8, "address": 120, "command": 222}, {"name": "INPUT AUX", "protocol": 8, "address": 120, "command": 222}, {"name": "INPUT AUX 2", "protocol": 8, "address": 120, "command": 222}, {"name": "INPUT: AUX 2", "protocol": 8, "address": 120, "command": 222}, {"name": "INPUT STB", "protocol": 8, "address": 120, "command": 223}, {"name": "INPUT TV", "protocol": 8, "address": 120, "command": 223}, {"name": "INPUT TV/STB", "protocol": 8, "address": 120, "command": 223}, {"name": "MUTE 20%", "protocol": 8, "address": 120, "command": 223}, {"name": "INPUT: TV/STB", "protocol": 8, "address": 120, "command": 223}]