[{"name": "S.TRACKING +", "protocol": 8, "address": 96, "command": 0}, {"name": "S.TRACKING -", "protocol": 8, "address": 96, "command": 1}, {"name": "S.SPEED +", "protocol": 8, "address": 96, "command": 2}, {"name": "S.SPEED -", "protocol": 8, "address": 96, "command": 3}, {"name": "8 (AM)", "protocol": 8, "address": 96, "command": 4}, {"name": "9 (PM)", "protocol": 8, "address": 96, "command": 5}, {"name": "F.FWD/VI.SRCH >>", "protocol": 8, "address": 96, "command": 9}, {"name": "REW/VI.SRCH <<", "protocol": 8, "address": 96, "command": 10}, {"name": "STOP []", "protocol": 8, "address": 96, "command": 11}, {"name": "0", "protocol": 8, "address": 96, "command": 12}, {"name": "1", "protocol": 8, "address": 96, "command": 13}, {"name": "2", "protocol": 8, "address": 96, "command": 14}, {"name": "3", "protocol": 8, "address": 96, "command": 15}, {"name": "F.ADV >", "protocol": 8, "address": 96, "command": 16}, {"name": "SLOW >", "protocol": 8, "address": 96, "command": 17}, {"name": "X2 FAST", "protocol": 8, "address": 96, "command": 18}, {"name": "PLAY >", "protocol": 8, "address": 96, "command": 20}, {"name": "REC/PLAY", "protocol": 8, "address": 96, "command": 20}, {"name": "OPERATE", "protocol": 8, "address": 96, "command": 23}, {"name": "CHANNEL -", "protocol": 8, "address": 96, "command": 24}, {"name": "CHANNEL +", "protocol": 8, "address": 96, "command": 25}, {"name": "PAUSE", "protocol": 8, "address": 96, "command": 26}, {"name": "REC/PAUSE", "protocol": 8, "address": 96, "command": 26}, {"name": "4", "protocol": 8, "address": 96, "command": 28}, {"name": "5", "protocol": 8, "address": 96, "command": 29}, {"name": "6", "protocol": 8, "address": 96, "command": 30}, {"name": "7 (WKL/DLY)", "protocol": 8, "address": 96, "command": 31}, {"name": "TRANS", "protocol": 8, "address": 96, "command": 64}, {"name": "COUNTER RESET", "protocol": 8, "address": 96, "command": 65}, {"name": "COUNTER MEMORY", "protocol": 8, "address": 96, "command": 68}, {"name": "UNKNOWN", "protocol": 8, "address": 96, "command": 69}, {"name": "REPEAT", "protocol": 8, "address": 96, "command": 71}]