[{"name": "KEY_0", "protocol": 17, "address": 5, "command": 0}, {"name": "KEY_1", "protocol": 17, "address": 5, "command": 1}, {"name": "KEY_2", "protocol": 17, "address": 5, "command": 2}, {"name": "KEY_3", "protocol": 17, "address": 5, "command": 3}, {"name": "KEY_4", "protocol": 17, "address": 5, "command": 4}, {"name": "KEY_5", "protocol": 17, "address": 5, "command": 5}, {"name": "KEY_6", "protocol": 17, "address": 5, "command": 6}, {"name": "KEY_7", "protocol": 17, "address": 5, "command": 7}, {"name": "KEY_8", "protocol": 17, "address": 5, "command": 8}, {"name": "KEY_9", "protocol": 17, "address": 5, "command": 9}, {"name": "switch_prgs", "protocol": 17, "address": 5, "command": 10}, {"name": "KEY_SLEEP", "protocol": 17, "address": 5, "command": 12}, {"name": "calibrate", "protocol": 17, "address": 5, "command": 14}, {"name": "prog", "protocol": 17, "address": 5, "command": 29}, {"name": "KEY_UP", "protocol": 17, "address": 5, "command": 32}, {"name": "KEY_DOWN", "protocol": 17, "address": 5, "command": 33}, {"name": "otr-rec", "protocol": 17, "address": 5, "command": 36}, {"name": "KEY_PAUSE", "protocol": 17, "address": 5, "command": 41}, {"name": "fast", "protocol": 17, "address": 5, "command": 42}, {"name": "pic_rew", "protocol": 17, "address": 5, "command": 44}, {"name": "pic_ff", "protocol": 17, "address": 5, "command": 46}, {"name": "KEY_REWIND", "protocol": 17, "address": 5, "command": 47}, {"name": "reset", "protocol": 17, "address": 5, "command": 49}, {"name": "KEY_REWIND", "protocol": 17, "address": 5, "command": 50}, {"name": "KEY_FASTFORWARD", "protocol": 17, "address": 5, "command": 52}, {"name": "KEY_PLAY", "protocol": 17, "address": 5, "command": 53}, {"name": "KEY_STOP", "protocol": 17, "address": 5, "command": 54}, {"name": "KEY_RECORD", "protocol": 17, "address": 5, "command": 55}]