[{"name": "STOP []", "protocol": 8, "address": 119, "command": 24}, {"name": "PLAY >", "protocol": 8, "address": 119, "command": 25}, {"name": "PAUSE ", "protocol": 8, "address": 119, "command": 26}, {"name": "REPEAT", "protocol": 8, "address": 119, "command": 27}, {"name": "SKIP <", "protocol": 8, "address": 119, "command": 28}, {"name": "SKIP >", "protocol": 8, "address": 119, "command": 29}, {"name": "FFWD >>", "protocol": 8, "address": 119, "command": 30}, {"name": "REW <<", "protocol": 8, "address": 119, "command": 31}, {"name": "C/AC", "protocol": 8, "address": 119, "command": 75}, {"name": "OPEN/CLOSE", "protocol": 8, "address": 119, "command": 76}, {"name": "REMAIN", "protocol": 8, "address": 119, "command": 77}, {"name": "MEMORY", "protocol": 8, "address": 119, "command": 78}]