[{"name": "PROGRAM", "protocol": 8, "address": 97, "command": 0}, {"name": "VCR PROGRAM", "protocol": 8, "address": 97, "command": 0}, {"name": "VCR1 S.Q.P.", "protocol": 8, "address": 97, "command": 0}, {"name": "RECORD", "protocol": 8, "address": 97, "command": 20}, {"name": "VTR RECORD", "protocol": 8, "address": 97, "command": 20}, {"name": "REC", "protocol": 8, "address": 97, "command": 20}, {"name": "VCR1 RECORD", "protocol": 8, "address": 97, "command": 20}, {"name": "VCR1 REC", "protocol": 8, "address": 97, "command": 20}, {"name": "VCR REC", "protocol": 8, "address": 97, "command": 20}, {"name": "VCR1 REC-PLAY", "protocol": 8, "address": 97, "command": 20}, {"name": "VTR1 RECORD", "protocol": 8, "address": 97, "command": 20}, {"name": "PL", "protocol": 8, "address": 97, "command": 64}]