[{"name": "KEY_LEFT", "protocol": 8, "address": 111, "command": 16}, {"name": "KEY_RIGHT", "protocol": 8, "address": 111, "command": 17}, {"name": "KEY_UP", "protocol": 8, "address": 111, "command": 18}, {"name": "KEY_DOWN", "protocol": 8, "address": 111, "command": 19}, {"name": "KEY_SELECT", "protocol": 8, "address": 111, "command": 20}, {"name": "KEY_EXIT", "protocol": 8, "address": 111, "command": 21}, {"name": "KEY_POWER", "protocol": 8, "address": 111, "command": 22}, {"name": "KEY_MENU", "protocol": 8, "address": 111, "command": 23}, {"name": "KEY_SEARCH", "protocol": 8, "address": 111, "command": 24}, {"name": "KEY_PLAY", "protocol": 8, "address": 111, "command": 25}, {"name": "KEY_NEXT", "protocol": 8, "address": 111, "command": 26}, {"name": "KEY_PREVIOUS", "protocol": 8, "address": 111, "command": 27}, {"name": "KEY_PAUSE", "protocol": 8, "address": 111, "command": 28}, {"name": "add", "protocol": 8, "address": 111, "command": 29}, {"name": "shuffle", "protocol": 8, "address": 111, "command": 30}, {"name": "KEY_AGAIN", "protocol": 8, "address": 111, "command": 31}, {"name": "KEY_VOLUMEUP", "protocol": 8, "address": 111, "command": 64}, {"name": "KEY_VOLUMEDOWN", "protocol": 8, "address": 111, "command": 65}, {"name": "bright", "protocol": 8, "address": 111, "command": 66}, {"name": "KEY_POWER", "protocol": 8, "address": 111, "command": 67}, {"name": "KEY_POWER", "protocol": 8, "address": 111, "command": 68}, {"name": "user1", "protocol": 8, "address": 111, "command": 69}, {"name": "user2", "protocol": 8, "address": 111, "command": 70}, {"name": "user3", "protocol": 8, "address": 111, "command": 71}, {"name": "user4", "protocol": 8, "address": 111, "command": 72}, {"name": "user5", "protocol": 8, "address": 111, "command": 73}, {"name": "user6", "protocol": 8, "address": 111, "command": 74}]